LICENSE
README.md
pyproject.toml
setup.cfg
setup.py
dress_diff/__init__.py
dress_diff/app.py
dress_diff.egg-info/PKG-INFO
dress_diff.egg-info/SOURCES.txt
dress_diff.egg-info/dependency_links.txt
dress_diff.egg-info/requires.txt
dress_diff.egg-info/top_level.txt
dress_diff/diffusion_models/__init__.py
dress_diff/diffusion_models/controlnet/__init__.py
dress_diff/diffusion_models/controlnet/controlnet_canny.py
dress_diff/diffusion_models/controlnet/controlnet_depth.py
dress_diff/diffusion_models/controlnet/controlnet_hed.py
dress_diff/diffusion_models/controlnet/controlnet_mlsd.py
dress_diff/diffusion_models/controlnet/controlnet_pose.py
dress_diff/diffusion_models/controlnet/controlnet_scribble.py
dress_diff/diffusion_models/controlnet/controlnet_seg.py
dress_diff/diffusion_models/stable_diffusion/__init__.py
dress_diff/diffusion_models/stable_diffusion/img2img_app.py
dress_diff/diffusion_models/stable_diffusion/text2img_app.py
dress_diff/upscaler_models/__init__.py
dress_diff/upscaler_models/codeformer_upscaler.py
dress_diff/utils/__init__.py
dress_diff/utils/model_list.py
dress_diff/utils/scheduler_list.py